[
  {
    "type": "video",
    "title": "iPhone 13 Mini Device Monitor Specification",
    "url": "https://youtu.be/hsVGr9wEXSo",
    "source": "YouTube",
    "lang": "EN"
  },
  {
    "type": "video",
    "title": "Haz tu iPhone MÁS RÁPIDO gracias a iOS 17",
    "url": "https://youtu.be/mF6UOEyFD90?t=133",
    "source": "YouTube",
    "lang": "ES"
  },
  {
    "type": "video",
    "title": "How To CLEAR iPhone RAM Memory on iOS 18!",
    "url": "https://youtu.be/lEwrhgEgtlg?t=180",
    "source": "YouTube",
    "lang": "EN"
  },
  {
    "type": "video",
    "title": "Mi iPhone está lento… SOLUCIÓN al LIBERAR la RAM",
    "url": "https://youtu.be/ai-Gdck68-A?t=212",
    "source": "YouTube",
    "lang": "ES"
  },
  {
    "type": "video",
    "title": "ฟรี! เคลียร์แรม ไม่ง้อปุ่ม iPhone และ iPad",
    "url": "https://youtu.be/p9NY_ff4f1E",
    "source": "YouTube",
    "lang": "TH"
  },
  {
    "type": "article",
    "title": "4 skvělé aplikace pro sledování systémových prostředků na iPhonu",
    "url": "https://www.letemsvetemapplem.eu/2025/01/26/4-skvele-aplikace-pro-sledovani-systemovych-prostredku-na-iphonu/",
    "source": "letemsvetemapplem.eu",
    "lang": "CS"
  }
]
